skripsi/__init__.py
skripsi-0.1.1.dist-info/LICENSE
skripsi-0.1.1.dist-info/WHEEL
skripsi-0.1.1.dist-info/METADATA
skripsi-0.1.1.dist-info/RECORD
